bootstrap/__init__.py
innodb_optimize-0.2.1.data/scripts/innodb-optimize
innodb_optimize-0.2.1.dist-info/LICENSE
innodb_optimize-0.2.1.dist-info/METADATA
innodb_optimize-0.2.1.dist-info/WHEEL
innodb_optimize-0.2.1.dist-info/top_level.txt
innodb_optimize-0.2.1.dist-info/RECORD
