Metadata-Version: 2.1
Name: innodb-optimize
Version: 0.2.1
Summary: Automated optimizer for MySQL InnoDB configurations
Home-page: https://github.com/Scraps23/innodb_optimize
Author: Ben Nassif
Author-email: bennassif@gmail.com
Maintainer: Ben Nassif
Maintainer-email: bennassif@gmail.com
License: 
Platform: UNKNOWN
Classifier: Development Status :: 4 - Beta
Classifier: Intended Audience :: Developers
Classifier: License :: OSI Approved :: MIT License
Classifier: Natural Language :: English
Classifier: Operating System :: Unix
Classifier: Operating System :: POSIX :: Linux
Classifier: Topic :: Database :: Database Engines/Servers
Classifier: Topic :: System :: Systems Administration
Classifier: Programming Language :: Python
Classifier: Programming Language :: Python :: 3.8
Classifier: Programming Language :: Python :: 3.9
Classifier: Programming Language :: Python :: 3.10
License-File: LICENSE
Requires-Dist: fire
Requires-Dist: psutil
